{
  "controller/Detail.controller.js": 1625562244000,
  "Router.js": 1625562244000,
  "util/Services.js": 1625562244000,
  "util/DataManager.js": 1625562244000,
  "util/Constants.js": 1625562244000,
  "util/Commons.js": 1625562244000,
  "controller/WhereUsed.controller.js": 1625562244000,
  "controller/Versions.controller.js": 1625562244000,
  "controller/Main.controller.js": 1625562244000,
  "i18n/i18n.properties": 1625562244000,
  "controller/App.controller.js": 1625562244000,
  "manifest.json": 1625573182818,
  "Component.js": 1625562244000,
  "manifest-bundle.zip": 1625573182866,
  "Component-preload.js": 1625573184741,
  "controller/Versions-dbg.controller.js": 1625562244000,
  "util/DataManager-dbg.js": 1625562244000,
  "util/Constants-dbg.js": 1625562244000,
  "util/Commons-dbg.js": 1625562244000,
  "controller/WhereUsed-dbg.controller.js": 1625562244000,
  "util/Services-dbg.js": 1625562244000,
  "controller/Main-dbg.controller.js": 1625562244000,
  "controller/Detail-dbg.controller.js": 1625562244000,
  "controller/App-dbg.controller.js": 1625562244000,
  "Router-dbg.js": 1625562244000,
  "Component-dbg.js": 1625562244000,
  "neo-app.json": 1625573185309,
  "di.code-validation.core_issues.json": 1625573190757,
  "resources.json": 1625573190950,
  "view/WhereUsed.view.xml": 1625562244000,
  "view/Versions.view.xml": 1625562244000,
  "view/Main.view.xml": 1625562244000,
  "view/Detail.view.xml": 1625562244000,
  "view/App.view.xml": 1625562244000,
  "css/style.css": 1625562244000,
  "index.html": 1625562244000
}